elm/__init__.py
elm.tree-0.0.1.dist-info/METADATA
elm.tree-0.0.1.dist-info/WHEEL
elm.tree-0.0.1.dist-info/top_level.txt
elm.tree-0.0.1.dist-info/RECORD
