Metadata-Version: 2.1
Name: elm.tree
Version: 0.0.1
Summary: Unbreakable encryption
Home-page: http://github.com/Ehnryu/elm-tree
Author: Ehnryu/Sakurai07
Author-email: blzzardst0rm@gmail.com
License: MIT
Keywords: encryption,elm
Platform: UNKNOWN
Classifier: Programming Language :: Python :: 3
